README.md
setup.py
dadjokes/__init__.py
dadjokes/__main__.py
dadjokes/main.py
dadjokes_plus_plus.egg-info/PKG-INFO
dadjokes_plus_plus.egg-info/SOURCES.txt
dadjokes_plus_plus.egg-info/dependency_links.txt
dadjokes_plus_plus.egg-info/entry_points.txt
dadjokes_plus_plus.egg-info/requires.txt
dadjokes_plus_plus.egg-info/top_level.txt